Workbook

Sheet Hoja 1
A1: FECHA | B1: MES | C1: SEMANA | D1: Nombre | E1: Apellido | F1: WhatsApp | G1: #Orden | H1: Pregunta 1 | I1: Pregunta 2 | J1: Click Google | K1: Premio Entregado por Asesor | L1: TALLER | M1: Fecha Premio Entregado | N1: Taller | O1: Referencia
A2: 46057 | B2: =+MONTH(A2) -> 2 | C2: =+WEEKNUM(A2) -> 6 | D2: SEBASTIAN | E2: BULLA | F2: 573002308392 | G2: 78670 | H2: Bueno | I2: Buena | J2: Buena movilidad y buen servicio. | K2: Inicio | M2: Taller av chile
A3: 46057 | B3: =+MONTH(A3) -> 2 | C3: =+WEEKNUM(A3) -> 6 | D3: RAFAEL ARAMIS | E3: PINZON RAMOS | F3: 573105583071 | G3: 78424 | H3: Bueno | I3: Buena | J3: Tener mas accesorios utiles para la patineta, mas personalizaciones, tener en cuentanla calidad de los accesorios ya que parece qje no fueran de buena calidad | K3: Inicio | M3: Minca Calle 72 con 24
A4: 46057 | B4: =+MONTH(A4) -> 2 | C4: =+WEEKNUM(A4) -> 6 | D4: JOSE | E4: LOPEZ TORRES | F4: 573213733338 | G4: 78667 | H4: Regular | I4: Buena | J4: La marca buena y la primer ida al taller pues no fue del todo satisfactoria. | M4: Chico
A5: 46057 | B5: =+MONTH(A5) -> 2 | C5: =+WEEKNUM(A5) -> 6 | D5: JUAN CARLOS | E5: GÓMEZ | F5: 573214518618 | G5: 78099 | H5: Bueno | I5: Buena | J5: Sin comentarios | K5: Inicio | M5: Calle 72
A6: 46057 | B6: =+MONTH(A6) -> 2 | C6: =+WEEKNUM(A6) -> 6 | D6: CRISTHIAN HERNANDO | E6: BOTERO YAIMA | F6: 573244760565 | G6: 78001 | H6: Bueno | I6: Buena | J6: Fue todo exelente desde la atención hasta como quedó la moto | K6: Inicio | M6: En el de Av chile
A7: 46057 | B7: =+MONTH(A7) -> 2 | C7: =+WEEKNUM(A7) -> 6 | D7: JULIAN | E7: CADAVID | F7: 573016559943 | G7: 78565 | H7: Bueno | I7: Buena | J7: Todo muy bien | K7: Inicio | M7: Cedritos
A8: 46057 | B8: =+MONTH(A8) -> 2 | C8: =+WEEKNUM(A8) -> 6 | D8: JUAN NICOLAS | E8: REYES RESTREPO | F8: 573214588554 | G8: 78246 | H8: Bueno | I8: Buena | J8: Lo único es que ayer se me hizo una cotización, y cuando pagué se había aumentado un adicional que subió mucho el costo y no me llegó una notificación de este cambio, no hubo problema pero creo que es algo de tener cuidado | K8: Inicio | M8: Chico
A9: 46057 | B9: =+MONTH(A9) -> 2 | C9: =+WEEKNUM(A9) -> 6 | D9: NORIS ISABEL | E9: ARIAS TAPIA | F9: 573135900380 | G9: 78298 | H9: Bueno | I9: Buena | J9: Es una excelente marca | K9: Inicio | M9: .
A10: 46057 | B10: =+MONTH(A10) -> 2 | C10: =+WEEKNUM(A10) -> 6 | D10: LINDA CAROLINA | E10: RUIZ MORALES | F10: 573232742435 | G10: 77636 | H10: Bueno | I10: Buena | J10: Me encantaría que sacaran baúles mas grandes para la moped | K10: Inicio | M10: Av Chile
A11: 46057 | B11: =+MONTH(A11) -> 2 | C11: =+WEEKNUM(A11) -> 6 | D11: LUCAS | E11: MESA MEJIA | F11: 573102619373 | G11: 77899 | H11: Bueno | I11: Buena | J11: Gracias | K11: Inicio | M11: .
A12: 46057 | B12: =+MONTH(A12) -> 2 | C12: =+WEEKNUM(A12) -> 6 | D12: NICOLAS ALEXANDER | E12: PINZON QUINTERO | F12: 573194141745 | G12: 78187 | H12: Bueno | I12: Buena | J12: Estuvo mejor la atención que las anteriores veces, me quedo un ruido en la patineta que iré el sábado a que me revisen | K12: Inicio | M12: Cedritos
A13: 46057 | B13: =+MONTH(A13) -> 2 | C13: =+WEEKNUM(A13) -> 6 | D13: BRIAN NORBERTO | E13: DIAZ OSPITIA | F13: 573023363600 | G13: 78093 | H13: Bueno | I13: Buena | J13: Excelente atención y trabajo mi Minca quedó perfecta muchas gracias! | K13: Inicio | M13: Cedritos
A14: 46057 | B14: =+MONTH(A14) -> 2 | C14: =+WEEKNUM(A14) -> 6 | D14: HAROLD ORLANDO | E14: GUZMAN UCEDA | F14: 573170111185 | G14: 78607 | H14: Bueno | I14: Buena | J14: Fui primero al taller de av chile, pero me atendieron super feo, por eso fui a chicó. | K14: Inicio | M14: Chico
A15: 46057 | B15: =+MONTH(A15) -> 2 | C15: =+WEEKNUM(A15) -> 6 | D15: CATERIN | E15: FRANCO FERNANDEZ | F15: 573058397345 | G15: 78564 | H15: Bueno | I15: Buena | J15: Muy buena | K15: Inicio | M15: Av 19
A16: 46057 | B16: =+MONTH(A16) -> 2 | C16: =+WEEKNUM(A16) -> 6 | D16: RAUL | E16: HIDALGO RODRIGUEZ | F16: 573134427727 | G16: 77865 | H16: Bueno | I16: Buena | J16: En general l la atención fue buena aunque . Sería bueno que tuvieran mejor stock de repuestos . Yo tuve que sacar la patineta sin pantalla porque la necesito usar. | K16: Inicio | M16: Créditos
A17: 46057 | B17: =+MONTH(A17) -> 2 | C17: =+WEEKNUM(A17) -> 6 | D17: SANTIAGO | E17: VALENCIA | F17: 573107852688 | G17: 76114 | H17: Bueno | I17: Buena | K17: Inicio | M17: 95
A18: 46057 | B18: =+MONTH(A18) -> 2 | C18: =+WEEKNUM(A18) -> 6 | D18: SAMUEL ANDRES | E18: ORTIZ ROMERO | F18: 573188665160 | G18: 78222 | H18: Bueno | I18: Buena | J18: Tuvo un pequeño detalle al momento de la entrega, fue solucionado de inmediato, entonces, 10 puntos | K18: Inicio | M18: Chicó
A19: 46057 | B19: =+MONTH(A19) -> 2 | C19: =+WEEKNUM(A19) -> 6 | D19: MONICA ALEJANDRA | E19: ORJUELA PRIETO | F19: 573203316724 | G19: 78038 | H19: Bueno | I19: Regular | J19: El mantenimiento fue bueno, solo que se demoraron bastante el el proceso, ya que segun los tiempo que me habían dado el dia lunes debían entregarme y hasta el día lunes empezó la revisión, significa que la patineta estuvo quita sin revisión desde el miércoles que la lleve | M19: Av chile
A20: 46057 | B20: =+MONTH(A20) -> 2 | C20: =+WEEKNUM(A20) -> 6 | D20: CARLOS ANDRES | E20: TAVERA ALPIZAR | F20: 573209927868 | G20: 78196 | H20: Bueno | I20: Buena | J20: El servicio es muy bueno y quede muy satisfecho con la revisión de mi patineta | K20: Inicio | M20: 140 con 19
A21: 46056 | B21: =+MONTH(A21) -> 2 | C21: =+WEEKNUM(A21) -> 6 | D21: OSCAR DANIEL | E21: HERRERA ZÁRATE | F21: 573186279231 | G21: 77930 | H21: Regular | I21: Buena | J21: Primero el 26 de enero me informaron que en 2 días estaría lista. Después que el 31, y tampoco estuvo lista y finalmente me la entregaron el 3 de febrero. Ni un mantenimiento general tarda tanto. Solamente era un cambio de piñón trasero | M21: Av Chile
A22: 46056 | B22: =+MONTH(A22) -> 2 | C22: =+WEEKNUM(A22) -> 6 | D22: ALEXANDER | E22: ROZO | F22: 573202630410 | G22: 77660 | H22: Bueno | I22: Buena | J22: un gran servicio con calidad y amabilidad | K22: Inicio | M22: Javeriana
A23: 46056 | B23: =+MONTH(A23) -> 2 | C23: =+WEEKNUM(A23) -> 6 | D23: DAVID ESTEBAN | E23: LOTERO GONZALEZ | F23: 573195505581 | G23: 78473 | H23: Bueno | I23: Buena | K23: Inicio | M23: Chico
A24: 46056 | B24: =+MONTH(A24) -> 2 | C24: =+WEEKNUM(A24) -> 6 | D24: JONATHAN DAVID | E24: TORRES | F24: 573002182101 | G24: 78209 | H24: Bueno | I24: Buena | J24: Excelente la mejor inversión | K24: Inicio | M24: Av chile
A25: 46056 | B25: =+MONTH(A25) -> 2 | C25: =+WEEKNUM(A25) -> 6 | D25: MATEO | E25: MORALES CORREA | F25: 573228136150 | G25: 78539 | H25: Bueno | I25: Buena | J25: Excelente marca buena calidad de esos productos | K25: Inicio | M25: Chico
A26: 46056 | B26: =+MONTH(A26) -> 2 | C26: =+WEEKNUM(A26) -> 6 | D26: DIANA MARCELA | E26: DIAZ CARO | F26: 573214560160 | G26: 78329 | H26: Bueno | I26: Buena | J26: Muchas gracias porque tomaron atenta nota de todos los detalles que tenía mi patineta y quedó como nueva 😄 | K26: Inicio | M26: Calle 72
A27: 46056 | B27: =+MONTH(A27) -> 2 | C27: =+WEEKNUM(A27) -> 6 | D27: GIOVANNY ALBERTO | E27: MONTOYA PINZON | F27: 573151422990 | G27: 78509 | H27: Bueno | I27: Buena | J27: Me encanta las herramientas tecnológicas que usan para agendar citas, hacer seguimiento y entrega. Sigan así! | K27: Inicio | M27: Calle 95
A28: 46056 | B28: =+MONTH(A28) -> 2 | C28: =+WEEKNUM(A28) -> 6 | D28: DIEGO ALEJANDRO | E28: SANABRIA CASTRO | F28: 573132209594 | G28: 78531 | H28: Bueno | I28: Buena | J28: Muy bien | K28: Inicio | M28: 72
A29: 46056 | B29: =+MONTH(A29) -> 2 | C29: =+WEEKNUM(A29) -> 6 | D29: JOSE SANTIAGO | E29: ACOSTA BERNAL | F29: 573132747206 | G29: 78066 | H29: Regular | I29: Regular | J29: Falta puntualidad | M29: calle 95
A30: 46056 | B30: =+MONTH(A30) -> 2 | C30: =+WEEKNUM(A30) -> 6 | D30: KAREN MARGARITA | E30: DE LA HOZ CASTRO | F30: 573507993254 | G30: 78517 | H30: Bueno | I30: Buena | J30: El servicio fue excelente, muy rápido y los chicos resuelven todas las dudas, y te explican muy bien todo | K30: Inicio | M30: Taller chicó
A31: 46056 | B31: =+MONTH(A31) -> 2 | C31: =+WEEKNUM(A31) -> 6 | D31: CRISTHIAN DANIEL | E31: BENITEZ MONTAÑO | F31: 573202734329 | G31: 78171 | H31: Bueno | I31: Buena | J31: Bien servicio y buena atención | K31: Inicio | M31: Chico
A32: 46056 | B32: =+MONTH(A32) -> 2 | C32: =+WEEKNUM(A32) -> 6 | D32: JACKSON | E32: JOSE SANTANA | F32: 573151495879 | G32: 78143 | H32: Bueno | I32: Buena | K32: Inicio | M32: .
A33: 46056 | B33: =+MONTH(A33) -> 2 | C33: =+WEEKNUM(A33) -> 6 | D33: FRANKLIN | E33: FAJARDO ESTUPIÑAN | F33: 573212972134 | G33: 77544 | H33: Bueno | I33: Buena | J33: Muy agradable el servicio, por parte de la familia Minca. Los recomiendo ampliamente. 🙏🙏🙏 | K33: Inicio | M33: Javeriana
A34: 46056 | B34: =+MONTH(A34) -> 2 | C34: =+WEEKNUM(A34) -> 6 | D34: ERNESTO | E34: PATARROYO | F34: 573142063672 | G34: 78545 | H34: Bueno | I34: Buena | J34: Muy buena atención la que se recibe en cedritros taller antes llevaba la patineta en al taller de chico son demasiado groseros y no prestan buena atención, desde ahí dejé de llevarla a ese lugar | K34: Inicio | M34: Cedritos
A35: 46056 | B35: =+MONTH(A35) -> 2 | C35: =+WEEKNUM(A35) -> 6 | D35: JOHANA | E35: MUÑOZ | F35: 573102485766 | G35: 78191 | H35: Bueno | I35: Buena | J35: Deben abrir más horarios en cedritos | K35: Inicio | M35: Chico
A36: 46056 | B36: =+MONTH(A36) -> 2 | C36: =+WEEKNUM(A36) -> 6 | D36: MILENA | E36: SOTO SANGUINO | F36: 573007152300 | G36: 78003 | H36: Bueno | I36: Buena | J36: Super. Mucho mejor que en la de la javeriana, allí la atención es menos amable. | K36: Inicio | M36: Calle 72
A37: 46056 | B37: =+MONTH(A37) -> 2 | C37: =+WEEKNUM(A37) -> 6 | D37: JORGE EDUARDO | E37: CARDONA MURIEL | F37: 573193377680 | G37: 78448 | H37: Bueno | I37: Buena | J37: Siempre son amables y puntuales con las entregas. | K37: Inicio | M37: Cedritos
A38: 46056 | B38: =+MONTH(A38) -> 2 | C38: =+WEEKNUM(A38) -> 6 | D38: NICOLAS | E38: SANMIGUEL GARCIA | F38: 573012013128 | G38: 78420 | H38: Bueno | I38: Buena | J38: Rápido el servicio y buen trabajo. Muchas gracias!! | K38: Inicio | M38: Chicó
A39: 46056 | B39: =+MONTH(A39) -> 2 | C39: =+WEEKNUM(A39) -> 6 | D39: DAVID EDUARDO | E39: JAIMES GOMEZ | F39: 573193032172 | G39: 78123 | H39: Bueno | I39: Buena | J39: Excelente todo | K39: Inicio | M39: Cedritos
A40: 46056 | B40: =+MONTH(A40) -> 2 | C40: =+WEEKNUM(A40) -> 6 | D40: VANESA | E40: NUNEZ JIMENEZ | F40: 573102001809 | G40: 78169 | H40: Bueno | I40: Buena | K40: Inicio | M40: 95
A41: 46055 | B41: =+MONTH(A41) -> 2 | C41: =+WEEKNUM(A41) -> 6 | D41: LUIS | E41: MUÑOZ | F41: 573163346061 | G41: 77071 | H41: Bueno | I41: Buena | K41: Inicio | M41: Las Vegas
A42: 46055 | B42: =+MONTH(A42) -> 2 | C42: =+WEEKNUM(A42) -> 6 | D42: SERGIO ALEJANDRO | E42: GAMBA RAMIREZ | F42: 573138154745 | G42: 78333 | H42: Bueno | I42: Buena | J42: Fue muy rápido | K42: Inicio | M42: Minca chico
A43: 46055 | B43: =+MONTH(A43) -> 2 | C43: =+WEEKNUM(A43) -> 6 | D43: YANKLI EMIRO | E43: PEROZO MENDOZA | F43: 573018601491 | G43: 78145 | H43: Bueno | I43: Buena | J43: Minca es una excelente marca | K43: Inicio | M43: CALLE 95 # 13 - 55
A44: 46055 | B44: =+MONTH(A44) -> 2 | C44: =+WEEKNUM(A44) -> 6 | D44: ALEJANDRO | E44: AMAYA MONROY | F44: 573026351250 | G44: 78388 | H44: Bueno | I44: Buena | J44: Genial | K44: Inicio | M44: Cedritos
A45: 46055 | B45: =+MONTH(A45) -> 2 | C45: =+WEEKNUM(A45) -> 6 | D45: CARLOS GUILLERMO | E45: CUETO GAVIRIA | F45: 573106901782 | G45: 77021 | H45: Regular | I45: Buena | J45: Es muy buena marca, no me gustó que les pedí en el taller que le hicieran mantenimiento a los rodamientos del mástil porque lo ví oxidado y al parecer no se lo hicieron, el resto de reparación me pareció buena Pero me quedó esa inquietud del mantenimiento del mástil | M45: Avenida chile
A46: 46055 | B46: =+MONTH(A46) -> 2 | C46: =+WEEKNUM(A46) -> 6 | D46: ANGEL FERNANDO | E46: RODRIGUEZ MORALES | F46: 573134475522 | G46: 78470 | H46: Bueno | I46: Buena | J46: Muy buena | K46: Inicio | M46: 78470
A47: 46055 | B47: =+MONTH(A47) -> 2 | C47: =+WEEKNUM(A47) -> 6 | D47: PABLO | E47: ARBELAEZ ECHEVERRI | F47: 573158990871 | G47: 77987 | H47: Bueno | I47: Buena | J47: Me pareció caro el servicio, pero es un buen servicio | K47: Inicio | M47: Avenida chile
A48: 46055 | B48: =+MONTH(A48) -> 2 | C48: =+WEEKNUM(A48) -> 6 | D48: FEDERICO | E48: ANDUJAR | F48: 573160103806 | G48: 78439 | H48: Bueno | I48: Buena | J48: Buen servicio, confiable. Sugerencia, tener algun servicio logistico de retiro de parinetas x domilicio que necesiten reparación con agenda. | K48: Inicio | M48: Av 19
A49: 46055 | B49: =+MONTH(A49) -> 2 | C49: =+WEEKNUM(A49) -> 6 | D49: SANTIAGO | E49: SALAZAR GUTIERREZ | F49: 573117698450 | G49: 78346 | H49: Bueno | I49: Buena | J49: Buen servicio y rápido | K49: Inicio | M49: Taller Chicó
A50: 46055 | B50: =+MONTH(A50) -> 2 | C50: =+WEEKNUM(A50) -> 6 | D50: CORREDOR GIL | E50: ERIK SANTIAGO | F50: 573228428681 | G50: 78379 | H50: Regular | I50: Regular | J50: Perdón la atención fue buena pero el servicio de mantenimiento regular. Dejé mi patineta para la instalación de guardabarros delantero la dejé desde el sábado y el día lunes me la entregaron. No son atentos al detalle, las llantas estaban con bajo aire, no realizaron esa verificación antes de entregarme la patineta, me di cuenta cuando ya estaba montado en ella Es importante que detalles como esos sea verificados. A uno como cliente le gusta . Y en mi trabajo suelo hacer algo parecido | M50: Av chile
A51: 46055 | B51: =+MONTH(A51) -> 2 | C51: =+WEEKNUM(A51) -> 6 | D51: ANGIE CATALINA | E51: ACOSTA CORTES | F51: 573173643569 | G51: 78305 | H51: Bueno | I51: Buena | J51: Siempre me atienden muy bien y dan solución a los problemas | K51: Inicio | M51: Chico
A52: 46055 | B52: =+MONTH(A52) -> 2 | C52: =+WEEKNUM(A52) -> 6 | D52: NESTOR JAVIER | E52: YAYA YAYA | F52: 573102440343 | G52: 78262 | H52: Malo | I52: Buena | J52: El servicio de despinchar realmente no tiene un valor agregado. La llevé a despinchar por primera vez porque pensé que por el valor que cobran (28.000) se ponía un buen parche y se hacía el vulcanizado pero le enterraron una goma que pareciera que se va a caer muy pronto, este tipo de despinchado lo hacen en cualquier montallantas por 10.000 y no toca esperar de un día para otro como fue mi caso. Al indagar con el asesor me indicó que es a criterio del técnico si pone eso o si coloca un parche, me parece que se debía buscar lo mejor para el cliente por ese valor. | K52: Clic | M52: Chicó
A53: 46055 | B53: =+MONTH(A53) -> 2 | C53: =+WEEKNUM(A53) -> 6 | D53: DAVID | E53: RODRIGUEZ BERNAL | F53: 573144291039 | G53: 78046 | H53: Bueno | I53: Buena | J53: Excelente servicio y rápido! | K53: Inicio | M53: Cedritos
A54: 46055 | B54: =+MONTH(A54) -> 2 | C54: =+WEEKNUM(A54) -> 6 | D54: NELSON ORLANDO | E54: PULIDO FERREIRA | F54: 573112100041 | G54: 78244 | H54: Bueno | I54: Buena | J54: Me ha ido muy bien cuando he necesitado los servicios. Felicitaciones | K54: Inicio | M54: Cedritos
A55: 46055 | B55: =+MONTH(A55) -> 2 | C55: =+WEEKNUM(A55) -> 6 | D55: OSCAR | E55: PEÑA CASTRO | F55: 573218237095 | G55: 78102 | H55: Bueno | I55: Buena | J55: Buen servicio | K55: Inicio | M55: Calle 72
A56: 46055 | B56: =+MONTH(A56) -> 2 | C56: =+WEEKNUM(A56) -> 6 | D56: JUAN CARLOS | E56: CARDONA GARCIA | F56: 573046249638 | G56: 78421 | H56: Bueno | I56: Buena | J56: Agua y tinto pa los clientes 🙊🤗 | K56: Inicio | M56: Las Vegas
A57: 46053 | B57: =+MONTH(A57) -> 1 | C57: =+WEEKNUM(A57) -> 5 | D57: MARIANA | E57: RIVADENEIRA | F57: 573016479333 | G57: 74384 | H57: Regular | I57: Mala | M57: Chico
A58: 46053 | B58: =+MONTH(A58) -> 1 | C58: =+WEEKNUM(A58) -> 5 | D58: KAREN YANETH | E58: ROJAS GUALDRON | F58: 573103103051 | G58: 77957 | H58: Bueno | I58: Buena | J58: Muy buen servicio, las personas son muy serviciales y la atención es rapida | K58: Inicio | M58: Showroom calle 72 Av. Chile
A59: 46053 | B59: =+MONTH(A59) -> 1 | C59: =+WEEKNUM(A59) -> 5 | D59: JAIME ANDRES | E59: INFANTE ROJAS | F59: 573183701759 | G59: 77780 | H59: Bueno | I59: Buena | J59: Pues todo bien aunque deberían cargar la batería | K59: Inicio | M59: Chico
A60: 46053 | B60: =+MONTH(A60) -> 1 | C60: =+WEEKNUM(A60) -> 5 | D60: ANDREA | E60: ACOSTA ACOSTA | F60: 573133140303 | G60: 77749 | H60: Bueno | I60: Buena | J60: Todo perfecto | K60: Inicio | M60: .
A61: 46053 | B61: =+MONTH(A61) -> 1 | C61: =+WEEKNUM(A61) -> 5 | D61: JOSE FRANCISCO | E61: BELTRAN GUZMAN | F61: 573158647059 | G61: 78330 | H61: Bueno | I61: Buena | J61: Excelente | K61: Inicio | M61: Cedritos
A62: 46053 | B62: =+MONTH(A62) -> 1 | C62: =+WEEKNUM(A62) -> 5 | D62: NICOLAS | E62: SANMIGUEL GARCIA | F62: 573012013128 | G62: 78374 | H62: Regular | I62: Regular | M62: Cedritos
A63: 46053 | B63: =+MONTH(A63) -> 1 | C63: =+WEEKNUM(A63) -> 5 | D63: JEISON | E63: CUELLAR | F63: 573006688076 | G63: 76822 | H63: Bueno | I63: Buena | J63: Muy buena 👌🏻 para la movilidad de la ciudad | K63: Inicio | M63: Av chile
A64: 46053 | B64: =+MONTH(A64) -> 1 | C64: =+WEEKNUM(A64) -> 5 | D64: DIKTYON | E64: S.A.S | F64: 573176698712 | G64: 77704 | H64: Bueno | I64: Buena | J64: Buen servicio | K64: Inicio | M64: Avenida chile
A65: 46053 | B65: =+MONTH(A65) -> 1 | C65: =+WEEKNUM(A65) -> 5 | D65: LUIS FERNANDO | E65: GUARIN CORREDOR | F65: 573213271654 | G65: 78234 | H65: Bueno | I65: Buena | J65: La Marca me parece espectacular, lo único es que la Patineta va a volver por Garantía ya que la Caña o Mástil quedó dura, los técnicos me explicaron que si la dejaban más suelta quedaría sonando, entonces Minca tienes un Problema de Calidad con esa pieza | K65: Inicio | L65: Jenifer Salamanca | M65: Avenida Chile
A66: 46053 | B66: =+MONTH(A66) -> 1 | C66: =+WEEKNUM(A66) -> 5 | D66: WILLIAM ANDRES | E66: ALVAREZ MOYA | F66: 573142365131 | G66: 78332 | H66: Bueno | I66: Buena | J66: Muchas gracias por la atención en el taller. Fue excelente y atendieron mi solicitud. | K66: Inicio | M66: Javeriana
A67: 46053 | B67: =+MONTH(A67) -> 1 | C67: =+WEEKNUM(A67) -> 5 | D67: ANGELA LILIANA | E67: NIÑO MANOSALVA | F67: 573115632014 | G67: 77688 | H67: Bueno | I67: Buena | J67: Gracias | K67: Inicio | M67: Cedritos
A68: 46053 | B68: =+MONTH(A68) -> 1 | C68: =+WEEKNUM(A68) -> 5 | D68: ANDRES AUGUSTO | E68: BELTRAN CUELLAR | F68: 573176869978 | G68: 77380 | H68: Bueno | I68: Buena | J68: Excelente servicio, solo que ya les quedó pequeño el taller | K68: Inicio | M68: Javeriana
A69: 46053 | B69: =+MONTH(A69) -> 1 | C69: =+WEEKNUM(A69) -> 5 | D69: KEVIN | E69: AISLINT | F69: 573102867528 | G69: 77792 | H69: Bueno | I69: Buena | J69: Excelente producto | K69: Inicio | M69: Cedritos
A70: 46053 | B70: =+MONTH(A70) -> 1 | C70: =+WEEKNUM(A70) -> 5 | D70: ANDRES ALFONSO | E70: DAZA OSMA | F70: 573133251023 | G70: 77942 | H70: Bueno | I70: Buena | J70: En general la atención bien, siento que a lo mejor el local se está quedando pequeño en la parte del taller porque siempre hay fila | K70: Inicio | M70: Avenida Chile
A71: 46053 | B71: =+MONTH(A71) -> 1 | C71: =+WEEKNUM(A71) -> 5 | D71: ELIZABETH | E71: CERMEÑO DIAZ | F71: 573158433295 | G71: 77947 | H71: Bueno | I71: Buena | J71: Excelente marca | K71: Inicio | M71: Cedritos
A72: 46052 | B72: =+MONTH(A72) -> 1 | C72: =+WEEKNUM(A72) -> 5 | D72: LEIDY | E72: QUIÑONES | F72: 573057650424 | G72: 77097 | H72: Malo | I72: Buena | M72: Av chile
A73: 46052 | B73: =+MONTH(A73) -> 1 | C73: =+WEEKNUM(A73) -> 5 | D73: ANDERSON | E73: SUAREZ | F73: 573182633123 | G73: 77596 | H73: Bueno | I73: Buena | J73: Sugerencia: 1. Entregar la patineta en el dia acordado ya que muchos la usamos como vehiculo y por un mantenimiento demorarse 8 dias, me parece mucho. 2. ⁠Ojala el mantenimiento lo realizaran en el horario que uno separa por la pagina web, es decir, yo elegi 10 am de un dia y pense que la podia esperar mientras le hacian el mantenimiento y demoró 8 dias | K73: Inicio | M73: Taller medellin, las vegas
A74: 46052 | B74: =+MONTH(A74) -> 1 | C74: =+WEEKNUM(A74) -> 5 | D74: NESTOR FERNANDO | E74: PENAGOS QUINTERO | F74: 573002186103 | G74: 78227 | H74: Bueno | I74: Buena | J74: Buena atención. | K74: Inicio | M74: Chico
A75: 46052 | B75: =+MONTH(A75) -> 1 | C75: =+WEEKNUM(A75) -> 5 | D75: LUIS AUGUSTO | E75: LASERNA ALVIRA | F75: 573158754047 | G75: 77843 | H75: Bueno | I75: Buena | J75: Buen servicio y muy rápido. | K75: Inicio | M75: Chico
A76: 46052 | B76: =+MONTH(A76) -> 1 | C76: =+WEEKNUM(A76) -> 5 | D76: JORGE EDUARDO | E76: REYES VARGAS | F76: 573143095789 | G76: 77837 | H76: Bueno | I76: Buena | J76: Excelente patineta, buen servicio de taller | K76: Inicio | M76: Av chile
A77: 46052 | B77: =+MONTH(A77) -> 1 | C77: =+WEEKNUM(A77) -> 5 | D77: WILLIAM ADRIAN | E77: RINCON BABATIVA | F77: 573334307291 | G77: 77558 | H77: Bueno | I77: Buena | J77: Tienen productos de muy buena calidad y buen servicio técnico | K77: Inicio | M77: Javeriana
A78: 46052 | B78: =+MONTH(A78) -> 1 | C78: =+WEEKNUM(A78) -> 5 | D78: DARIO ALDEMAR | E78: SANDOVAL LEON | F78: 573105593290 | G78: 77918 | H78: Bueno | I78: Buena | J78: Llevo 10 meses con la marca y a sido una experiencia muy positiva, en cuanto a movilidad, servicio y experiencia. Muchas gracias a minca por ese respaldo. | K78: Inicio | M78: Chico
A79: 46052 | B79: =+MONTH(A79) -> 1 | C79: =+WEEKNUM(A79) -> 5 | D79: JUAN DAVID | E79: PEÑA | F79: 573108174632 | G79: 77697 | H79: Bueno | I79: Regular | J79: Me parece excesivamente costos el mantenimiento, se dañó mi soporte trasero para cargar la patineta y estaba por garantía y nunca me lo han repuesto | M79: Javeriana
A80: 46052 | B80: =+MONTH(A80) -> 1 | C80: =+WEEKNUM(A80) -> 5 | D80: WILLIAN ALEXANDER | E80: JIMENEZ ORTIZ | F80: 573133659078 | G80: 77931 | H80: Bueno | I80: Buena | J80: Con Minca Ando Rodando! | K80: Inicio | M80: Cll 72
A81: 46052 | B81: =+MONTH(A81) -> 1 | C81: =+WEEKNUM(A81) -> 5 | D81: MARIA ANGELICA | E81: QUEVEDO CUENCA | F81: 573057517341 | G81: 77873 | H81: Bueno | I81: Buena | K81: Inicio | M81: Chile
A82: 46052 | B82: =+MONTH(A82) -> 1 | C82: =+WEEKNUM(A82) -> 5 | D82: CARLOS ANDRES | E82: PACHECO ARRIETA | F82: 573127259802 | G82: 78149 | H82: Bueno | I82: Buena | J82: En el momento soy nuevo con la marca pero me parece genial muy buena al igual que la atención en los talleres de la marca mi calificación 10 de 10 | K82: Inicio | M82: Taller chico
A83: 46052 | B83: =+MONTH(A83) -> 1 | C83: =+WEEKNUM(A83) -> 5 | D83: JAVIER | E83: GARCÍA | F83: 573150127601 | G83: 78129 | H83: Bueno | I83: Buena | J83: Pese a ser muy estrictos con el orden de llegada de los equipos para recibir servicio técnico, me ayudaron rápidamente con mi solicitud. La atención es de primer nivel, el equipo humano muy atento y en general la experiencia fue bastante positiva | K83: Inicio | M83: Chicó
A84: 46051 | B84: =+MONTH(A84) -> 1 | C84: =+WEEKNUM(A84) -> 5 | D84: ALEJANDRO | E84: ALVARADO RODRIGUEZ | F84: 573162280177 | G84: 78122 | H84: Bueno | I84: Buena | J84: Exelente atención | K84: Inicio | M84: Av chile
A85: 46051 | B85: =+MONTH(A85) -> 1 | C85: =+WEEKNUM(A85) -> 5 | D85: JULIAN CAMILO | E85: GRANADOS BOTIA | F85: 573246802086 | G85: 77861 | H85: Bueno | I85: Buena | K85: Inicio | M85: Javeriana
A86: 46051 | B86: =+MONTH(A86) -> 1 | C86: =+WEEKNUM(A86) -> 5 | D86: JULIAN CAMILO | E86: GRANADOS BOTIA | F86: 573246802086 | G86: 77861 | H86: Bueno | I86: Buena | J86: Muy buena experiencia siempre atento con los clientes con cualquier requerimiento | K86: Inicio | M86: Javeriana
A87: 46051 | B87: =+MONTH(A87) -> 1 | C87: =+WEEKNUM(A87) -> 5 | D87: NOVO | E87: NORDISK | F87: 573158593917 | G87: 78147 | H87: Bueno | I87: Buena | J87: Mi cita básicamente fue por que la llanta llegó con alguna perforación y ellos la despincharon y ya ! Gracias por la atención | K87: Inicio | M87: 142
A88: 46051 | B88: =+MONTH(A88) -> 1 | C88: =+WEEKNUM(A88) -> 5 | D88: MARÍA CAMILA | E88: GUTIÉRREZ GUTIÉRREZ | F88: 573166968395 | G88: 77452 | H88: Bueno | I88: Buena | J88: Explicar siempre bien cada proceso que realizan, mi inseguridad fue por una experiencia mala que tuve antes en la que me cambiaron una parte sin notificarme pero me di cuenta, entonces ahorita estaba prevenida con ese tema… pero el señor Jonathan que me entregó la patineta fue muy atento y me explicó detalladamente lo que le realizó. Gracias | K88: Inicio | M88: Av Chile
A89: 46051 | B89: =+MONTH(A89) -> 1 | C89: =+WEEKNUM(A89) -> 5 | D89: RODRIGO EDUARDO | E89: MELENDEZ CAMARGO | F89: 573164784838 | G89: 77159 | H89: Regular | I89: Buena | M89: CHICO
A90: 46051 | B90: =+MONTH(A90) -> 1 | C90: =+WEEKNUM(A90) -> 5 | D90: JOHN ALEXANDER | E90: SALGADO MUÑOZ | F90: 573206928494 | G90: 77912 | H90: Bueno | I90: Buena | J90: El servicio es excelente sin ninguna queja | K90: Inicio | M90: 143
A91: 46051 | B91: =+MONTH(A91) -> 1 | C91: =+WEEKNUM(A91) -> 5 | D91: CARLOS ALBERTO | E91: ECHEVERRY | F91: 573123178702 | G91: 77744 | H91: Bueno | I91: Buena | J91: Excelente servicio | K91: Inicio | M91: Chico
A92: 46051 | B92: =+MONTH(A92) -> 1 | C92: =+WEEKNUM(A92) -> 5 | D92: MARIA ALEJANDRA | E92: RODRIGUEZ | F92: 573102481860 | G92: 77720 | H92: Bueno | I92: Buena | J92: Servicio rápido y efectivo. | K92: Inicio | L92: Manuela prieto | M92: Javeriana
A93: 46051 | B93: =+MONTH(A93) -> 1 | C93: =+WEEKNUM(A93) -> 5 | D93: FELIPE | E93: TRUJILLO | F93: 573203339168 | G93: 76686 | H93: Bueno | I93: Buena | J93: Buen servicio, el reporte de mecánica es bueno pero podría mejorar incluyendo recomendaciones para el próximo servicio. De largo plazo, aunque es difícil, un servicio pago de domicilio de mantenimiento sería muy bueno | K93: Inicio | M93: Cl 95
A94: 46051 | B94: =+MONTH(A94) -> 1 | C94: =+WEEKNUM(A94) -> 5 | D94: CARLOS ANDRES | E94: ROMAN PACHECO | F94: 573115675533 | G94: 78072 | H94: Bueno | I94: Buena | J94: El precio malo | K94: Inicio | M94: Av chile
A95: 46051 | B95: =+MONTH(A95) -> 1 | C95: =+WEEKNUM(A95) -> 5 | D95: KAREN JULIETH | E95: LEON GARZON | F95: 573214363958 | G95: 77331 | H95: Bueno | I95: Buena | J95: Gracias, el servicio es bueno y la atención también sin embargo fue un poco demorado y si me afectó en mi rutina. | K95: Inicio | M95: Av chile
A96: 46051 | B96: =+MONTH(A96) -> 1 | C96: =+WEEKNUM(A96) -> 5 | D96: FABIAN | E96: CASTAÑEDA GARZON | F96: 573114521301 | G96: 78142 | H96: Bueno | I96: Buena | J96: Rápida la entrega de mi minca | K96: Inicio | M96: Taller de la calle 95
A97: 46051 | B97: =+MONTH(A97) -> 1 | C97: =+WEEKNUM(A97) -> 5 | D97: ANDRES JULIAN | E97: HENAO LOPEZ | F97: 573154861588 | G97: 77515 | H97: Bueno | I97: Buena | J97: Muy buena atención por parte del técnico | K97: Inicio | M97: Medellín las Vegas
A98: 46051 | B98: =+MONTH(A98) -> 1 | C98: =+WEEKNUM(A98) -> 5 | D98: VALERIA | E98: JIMENEZ GARCIA | F98: 573107711289 | G98: 78010 | H98: Bueno | I98: Buena | J98: Buena atención. | K98: Inicio | M98: 93
A99: 46051 | B99: =+MONTH(A99) -> 1 | C99: =+WEEKNUM(A99) -> 5 | D99: CRISTIAN ALBEIRO | E99: LOPEZ HENAO | F99: 573116260770 | G99: 77551 | H99: Regular | I99: Buena | J99: Revisar bien el trabajo realizado la llanta quedó golpeando el guardabarros | M99: Minca las vegas medellin
A100: 46051 | B100: =+MONTH(A100) -> 1 | C100: =+WEEKNUM(A100) -> 5 | D100: ANDRES FELIPE | E100: MACIAS TIBASOSA | F100: 573183813734 | G100: 77806 | H100: Bueno | I100: Buena | J100: Excelente | K100: Inicio | M100: Javeriana
...

Sheet Hoja3
A19: MES | B19: (Varios elementos) | G19: MES | H19: (Varios elementos)
A20: SEMANA | B20: 4 | G20: SEMANA | H20: 4
A22: Etiquetas de fila | B22: Cuenta de Pregunta 1 | G22: Etiquetas de fila | H22: Cuenta de Pregunta 2
A23: Bueno | B23: 41 | G23: Buena | H23: 41
A24: Malo | B24: 5 | G24: Regular | H24: 5
A25: Total general | B25: 46 | G25: Total general | H25: 46

Sheet MANYCHAT_SERVICE_SHEET
A3: =IFERROR(__xludf.DUMMYFUNCTION("QUERY('Hoja 1'!E1:E1000, ""SELECT * WHERE E=69520 OR E='69520' LIMIT 1"", 0)"),69520) -> 69520 | B3: =MATCH(A3,'Hoja 1'!G1:G892,0) -> #N/A
A6: =IFERROR(__xludf.DUMMYFUNCTION("QUERY('Hoja 1'!E1:E1000, ""SELECT * WHERE E=69520 OR E='69520' LIMIT 1"", 0)"),69520) -> 69520 | B6: =MATCH(A6,'Hoja 1'!G1:G892,0) -> #N/A
A9: =IFERROR(__xludf.DUMMYFUNCTION("QUERY('Hoja 1'!E1:E1000, ""SELECT * WHERE E=69520 OR E='69520' LIMIT 1"", 0)"),69520) -> 69520 | B9: =MATCH(A9,'Hoja 1'!G1:G892,0) -> #N/A
A12: =IFERROR(__xludf.DUMMYFUNCTION("QUERY('Hoja 1'!E1:E1000, ""SELECT * WHERE E=69520 OR E='69520' LIMIT 1"", 0)"),69520) -> 69520 | B12: =MATCH(A12,'Hoja 1'!G1:G892,0) -> #N/A
A15: =IFERROR(__xludf.DUMMYFUNCTION("QUERY('Hoja 1'!E1:E1000, ""SELECT * WHERE E=69520 OR E='69520' LIMIT 1"", 0)"),69520) -> 69520 | B15: =MATCH(A15,'Hoja 1'!G1:G892,0) -> #N/A
A18: =IFERROR(__xludf.DUMMYFUNCTION("QUERY('Hoja 1'!E1:E1000, ""SELECT * WHERE E=69651 OR E='69651' LIMIT 1"", 0)"),69651) -> 69651 | B18: =MATCH(A18,'Hoja 1'!G1:G892,0) -> #N/A
A21: =IFERROR(__xludf.DUMMYFUNCTION("QUERY('Hoja 1'!E1:E1000, ""SELECT * WHERE E=69651 OR E='69651' LIMIT 1"", 0)"),69651) -> 69651 | B21: =MATCH(A21,'Hoja 1'!G1:G892,0) -> #N/A
A24: =IFERROR(__xludf.DUMMYFUNCTION("QUERY('Hoja 1'!E1:E1000, ""SELECT * WHERE E=69688 OR E='69688' LIMIT 1"", 0)"),69688) -> 69688 | B24: =MATCH(A24,'Hoja 1'!G1:G892,0) -> #N/A
A27: =IFERROR(__xludf.DUMMYFUNCTION("QUERY('Hoja 1'!E1:E1000, ""SELECT * WHERE E=69651 OR E='69651' LIMIT 1"", 0)"),69651) -> 69651 | B27: =MATCH(A27,'Hoja 1'!G1:G892,0) -> #N/A
A30: =IFERROR(__xludf.DUMMYFUNCTION("QUERY('Hoja 1'!E1:E1000, ""SELECT * WHERE E=69688 OR E='69688' LIMIT 1"", 0)"),69688) -> 69688 | B30: =MATCH(A30,'Hoja 1'!G1:G892,0) -> #N/A
A33: =IFERROR(__xludf.DUMMYFUNCTION("QUERY('Hoja 1'!E1:E1000, ""SELECT * WHERE E=69651 OR E='69651' LIMIT 1"", 0)"),69651) -> 69651 | B33: =MATCH(A33,'Hoja 1'!G1:G892,0) -> #N/A
A36: =IFERROR(__xludf.DUMMYFUNCTION("QUERY('Hoja 1'!E1:E1000, ""SELECT * WHERE E=69651 OR E='69651' LIMIT 1"", 0)"),69651) -> 69651 | B36: =MATCH(A36,'Hoja 1'!G1:G892,0) -> #N/A
A39: =IFERROR(__xludf.DUMMYFUNCTION("QUERY('Hoja 1'!E1:E1000, ""SELECT * WHERE E=69990 OR E='69990' LIMIT 1"", 0)"),69990) -> 69990 | B39: =MATCH(A39,'Hoja 1'!G1:G892,0) -> #N/A
A42: =IFERROR(__xludf.DUMMYFUNCTION("QUERY('Hoja 1'!E1:E1000, ""SELECT * WHERE E=69990 OR E='69990' LIMIT 1"", 0)"),69990) -> 69990 | B42: =MATCH(A42,'Hoja 1'!G1:G892,0) -> #N/A
A45: =IFERROR(__xludf.DUMMYFUNCTION("QUERY('Hoja 1'!E1:E1000, ""SELECT * WHERE E=69990 OR E='69990' LIMIT 1"", 0)"),69990) -> 69990 | B45: =MATCH(A45,'Hoja 1'!G1:G892,0) -> #N/A
A48: =IFERROR(__xludf.DUMMYFUNCTION("QUERY('Hoja 1'!E1:E1000, ""SELECT * WHERE E=69933 OR E='69933' LIMIT 1"", 0)"),69933) -> 69933 | B48: =MATCH(A48,'Hoja 1'!G1:G892,0) -> #N/A
A51: =IFERROR(__xludf.DUMMYFUNCTION("QUERY('Hoja 1'!E1:E1000, ""SELECT * WHERE E=69933 OR E='69933' LIMIT 1"", 0)"),69933) -> 69933 | B51: =MATCH(A51,'Hoja 1'!G1:G892,0) -> #N/A
A54: =IFERROR(__xludf.DUMMYFUNCTION("QUERY('Hoja 1'!E1:E1000, ""SELECT * WHERE E=70281 OR E='70281' LIMIT 1"", 0)"),70281) -> 70281 | B54: =MATCH(A54,'Hoja 1'!G1:G892,0) -> #N/A
A57: =IFERROR(__xludf.DUMMYFUNCTION("QUERY('Hoja 1'!E1:E1000, ""SELECT * WHERE E=70281 OR E='70281' LIMIT 1"", 0)"),70281) -> 70281 | B57: =MATCH(A57,'Hoja 1'!G1:G892,0) -> #N/A
A60: =IFERROR(__xludf.DUMMYFUNCTION("QUERY('Hoja 1'!E1:E1000, ""SELECT * WHERE E=70261 OR E='70261' LIMIT 1"", 0)"),70261) -> 70261 | B60: =MATCH(A60,'Hoja 1'!G1:G892,0) -> #N/A
A63: =IFERROR(__xludf.DUMMYFUNCTION("QUERY('Hoja 1'!E1:E1000, ""SELECT * WHERE E=68840 OR E='68840' LIMIT 1"", 0)"),68840) -> 68840 | B63: =MATCH(A63,'Hoja 1'!G1:G892,0) -> #N/A
A66: =IFERROR(__xludf.DUMMYFUNCTION("QUERY('Hoja 1'!E1:E1000, ""SELECT * WHERE E=70261 OR E='70261' LIMIT 1"", 0)"),70261) -> 70261 | B66: =MATCH(A66,'Hoja 1'!G1:G892,0) -> #N/A
A69: =IFERROR(__xludf.DUMMYFUNCTION("QUERY('Hoja 1'!E1:E1000, ""SELECT * WHERE E=70261 OR E='70261' LIMIT 1"", 0)"),70261) -> 70261 | B69: =MATCH(A69,'Hoja 1'!G1:G892,0) -> #N/A
A72: =IFERROR(__xludf.DUMMYFUNCTION("QUERY('Hoja 1'!E1:E1000, ""SELECT * WHERE E=68840 OR E='68840' LIMIT 1"", 0)"),68840) -> 68840 | B72: =MATCH(A72,'Hoja 1'!G1:G892,0) -> #N/A
A75: =IFERROR(__xludf.DUMMYFUNCTION("QUERY('Hoja 1'!E1:E1000, ""SELECT * WHERE E=70261 OR E='70261' LIMIT 1"", 0)"),70261) -> 70261 | B75: =MATCH(A75,'Hoja 1'!G1:G892,0) -> #N/A
A78: =IFERROR(__xludf.DUMMYFUNCTION("QUERY('Hoja 1'!E1:E1000, ""SELECT * WHERE E=68840 OR E='68840' LIMIT 1"", 0)"),68840) -> 68840 | B78: =MATCH(A78,'Hoja 1'!G1:G892,0) -> #N/A
A81: =IFERROR(__xludf.DUMMYFUNCTION("QUERY('Hoja 1'!E1:E1000, ""SELECT * WHERE E=70188 OR E='70188' LIMIT 1"", 0)"),70188) -> 70188 | B81: =MATCH(A81,'Hoja 1'!G1:G892,0) -> #N/A
A84: =IFERROR(__xludf.DUMMYFUNCTION("QUERY('Hoja 1'!E1:E1000, ""SELECT * WHERE E=67274 OR E='67274' LIMIT 1"", 0)"),67274) -> 67274 | B84: =MATCH(A84,'Hoja 1'!G1:G892,0) -> #N/A
A87: =IFERROR(__xludf.DUMMYFUNCTION("QUERY('Hoja 1'!E1:E1000, ""SELECT * WHERE E=67274 OR E='67274' LIMIT 1"", 0)"),67274) -> 67274 | B87: =MATCH(A87,'Hoja 1'!G1:G892,0) -> #N/A
A90: =IFERROR(__xludf.DUMMYFUNCTION("QUERY('Hoja 1'!E1:E1000, ""SELECT * WHERE E=67274 OR E='67274' LIMIT 1"", 0)"),67274) -> 67274 | B90: =MATCH(A90,'Hoja 1'!G1:G892,0) -> #N/A
A93: =IFERROR(__xludf.DUMMYFUNCTION("QUERY('Hoja 1'!E1:E1000, ""SELECT * WHERE E=67933 OR E='67933' LIMIT 1"", 0)"),67933) -> 67933 | B93: =MATCH(A93,'Hoja 1'!G1:G892,0) -> #N/A
A96: =IFERROR(__xludf.DUMMYFUNCTION("QUERY('Hoja 1'!E1:E1000, ""SELECT * WHERE E=67933 OR E='67933' LIMIT 1"", 0)"),67933) -> 67933 | B96: =MATCH(A96,'Hoja 1'!G1:G892,0) -> #N/A
A99: =IFERROR(__xludf.DUMMYFUNCTION("QUERY('Hoja 1'!E1:E1000, ""SELECT * WHERE E=67933 OR E='67933' LIMIT 1"", 0)"),67933) -> 67933 | B99: =MATCH(A99,'Hoja 1'!G1:G892,0) -> #N/A
A102: =IFERROR(__xludf.DUMMYFUNCTION("QUERY('Hoja 1'!E1:E1000, ""SELECT * WHERE E=67933 OR E='67933' LIMIT 1"", 0)"),67933) -> 67933 | B102: =MATCH(A102,'Hoja 1'!G1:G892,0) -> #N/A
A105: =IFERROR(__xludf.DUMMYFUNCTION("QUERY('Hoja 1'!E1:E1000, ""SELECT * WHERE E=67933 OR E='67933' LIMIT 1"", 0)"),67933) -> 67933 | B105: =MATCH(A105,'Hoja 1'!G1:G892,0) -> #N/A
A108: =IFERROR(__xludf.DUMMYFUNCTION("QUERY('Hoja 1'!E1:E1000, ""SELECT * WHERE E=67251 OR E='67251' LIMIT 1"", 0)"),67251) -> 67251 | B108: =MATCH(A108,'Hoja 1'!G1:G892,0) -> #N/A
A111: =IFERROR(__xludf.DUMMYFUNCTION("QUERY('Hoja 1'!E1:E1000, ""SELECT * WHERE E=67251 OR E='67251' LIMIT 1"", 0)"),67251) -> 67251 | B111: =MATCH(A111,'Hoja 1'!G1:G892,0) -> #N/A
A114: =IFERROR(__xludf.DUMMYFUNCTION("QUERY('Hoja 1'!E1:E1000, ""SELECT * WHERE E=67251 OR E='67251' LIMIT 1"", 0)"),67251) -> 67251 | B114: =MATCH(A114,'Hoja 1'!G1:G892,0) -> #N/A
A117: =IFERROR(__xludf.DUMMYFUNCTION("QUERY('Hoja 1'!E1:E1000, ""SELECT * WHERE E=67251 OR E='67251' LIMIT 1"", 0)"),67251) -> 67251 | B117: =MATCH(A117,'Hoja 1'!G1:G892,0) -> #N/A
A120: =IFERROR(__xludf.DUMMYFUNCTION("QUERY('Hoja 1'!E1:E1000, ""SELECT * WHERE E=67251 OR E='67251' LIMIT 1"", 0)"),67251) -> 67251 | B120: =MATCH(A120,'Hoja 1'!G1:G892,0) -> #N/A
A123: =IFERROR(__xludf.DUMMYFUNCTION("QUERY('Hoja 1'!E1:E1000, ""SELECT * WHERE E=67251 OR E='67251' LIMIT 1"", 0)"),67251) -> 67251 | B123: =MATCH(A123,'Hoja 1'!G1:G892,0) -> #N/A
A126: =IFERROR(__xludf.DUMMYFUNCTION("QUERY('Hoja 1'!E1:E1000, ""SELECT * WHERE E=67251 OR E='67251' LIMIT 1"", 0)"),67251) -> 67251 | B126: =MATCH(A126,'Hoja 1'!G1:G892,0) -> #N/A
A129: =IFERROR(__xludf.DUMMYFUNCTION("QUERY('Hoja 1'!E1:E1000, ""SELECT * WHERE E=67955 OR E='67955' LIMIT 1"", 0)"),67955) -> 67955 | B129: =MATCH(A129,'Hoja 1'!G1:G892,0) -> #N/A
A132: =IFERROR(__xludf.DUMMYFUNCTION("QUERY('Hoja 1'!E1:E1000, ""SELECT * WHERE E=67955 OR E='67955' LIMIT 1"", 0)"),67955) -> 67955 | B132: =MATCH(A132,'Hoja 1'!G1:G892,0) -> #N/A
A135: =IFERROR(__xludf.DUMMYFUNCTION("QUERY('Hoja 1'!E1:E1000, ""SELECT * WHERE E=68022 OR E='68022' LIMIT 1"", 0)"),68022) -> 68022 | B135: =MATCH(A135,'Hoja 1'!G1:G892,0) -> #N/A
A138: =IFERROR(__xludf.DUMMYFUNCTION("QUERY('Hoja 1'!E1:E1000, ""SELECT * WHERE E=68022 OR E='68022' LIMIT 1"", 0)"),68022) -> 68022 | B138: =MATCH(A138,'Hoja 1'!G1:G892,0) -> #N/A
A141: =IFERROR(__xludf.DUMMYFUNCTION("QUERY('Hoja 1'!E1:E1000, ""SELECT * WHERE E=68022 OR E='68022' LIMIT 1"", 0)"),68022) -> 68022 | B141: =MATCH(A141,'Hoja 1'!G1:G892,0) -> #N/A
A144: =IFERROR(__xludf.DUMMYFUNCTION("QUERY('Hoja 1'!E1:E1000, ""SELECT * WHERE E=67829 OR E='67829' LIMIT 1"", 0)"),67829) -> 67829 | B144: =MATCH(A144,'Hoja 1'!G1:G892,0) -> #N/A
A147: =IFERROR(__xludf.DUMMYFUNCTION("QUERY('Hoja 1'!E1:E1000, ""SELECT * WHERE E=67829 OR E='67829' LIMIT 1"", 0)"),67829) -> 67829 | B147: =MATCH(A147,'Hoja 1'!G1:G892,0) -> #N/A
A150: =IFERROR(__xludf.DUMMYFUNCTION("QUERY('Hoja 1'!E1:E1000, ""SELECT * WHERE E=67829 OR E='67829' LIMIT 1"", 0)"),67829) -> 67829 | B150: =MATCH(A150,'Hoja 1'!G1:G892,0) -> #N/A
A153: =IFERROR(__xludf.DUMMYFUNCTION("QUERY('Hoja 1'!E1:E1000, ""SELECT * WHERE E=67829 OR E='67829' LIMIT 1"", 0)"),67829) -> 67829 | B153: =MATCH(A153,'Hoja 1'!G1:G892,0) -> #N/A
A156: =IFERROR(__xludf.DUMMYFUNCTION("QUERY('Hoja 1'!E1:E1000, ""SELECT * WHERE E=67893 OR E='67893' LIMIT 1"", 0)"),67893) -> 67893 | B156: =MATCH(A156,'Hoja 1'!G1:G892,0) -> #N/A
A159: =IFERROR(__xludf.DUMMYFUNCTION("QUERY('Hoja 1'!E1:E1000, ""SELECT * WHERE E=67893 OR E='67893' LIMIT 1"", 0)"),67893) -> 67893 | B159: =MATCH(A159,'Hoja 1'!G1:G892,0) -> #N/A
A162: =IFERROR(__xludf.DUMMYFUNCTION("QUERY('Hoja 1'!E1:E1000, ""SELECT * WHERE E=67893 OR E='67893' LIMIT 1"", 0)"),67893) -> 67893 | B162: =MATCH(A162,'Hoja 1'!G1:G892,0) -> #N/A
A165: =IFERROR(__xludf.DUMMYFUNCTION("QUERY('Hoja 1'!E1:E1000, ""SELECT * WHERE E=67914 OR E='67914' LIMIT 1"", 0)"),67914) -> 67914 | B165: =MATCH(A165,'Hoja 1'!G1:G892,0) -> #N/A
A168: =IFERROR(__xludf.DUMMYFUNCTION("QUERY('Hoja 1'!E1:E1000, ""SELECT * WHERE E=67910 OR E='67910' LIMIT 1"", 0)"),67910) -> 67910 | B168: =MATCH(A168,'Hoja 1'!G1:G892,0) -> #N/A
A171: =IFERROR(__xludf.DUMMYFUNCTION("QUERY('Hoja 1'!E1:E1000, ""SELECT * WHERE E=64476 OR E='64476' LIMIT 1"", 0)"),64476) -> 64476 | B171: =MATCH(A171,'Hoja 1'!G1:G892,0) -> #N/A
A174: =IFERROR(__xludf.DUMMYFUNCTION("QUERY('Hoja 1'!E1:E1000, ""SELECT * WHERE E=64476 OR E='64476' LIMIT 1"", 0)"),64476) -> 64476 | B174: =MATCH(A174,'Hoja 1'!G1:G892,0) -> #N/A
A177: =IFERROR(__xludf.DUMMYFUNCTION("QUERY('Hoja 1'!E1:E1000, ""SELECT * WHERE E=67829 OR E='67829' LIMIT 1"", 0)"),67829) -> 67829 | B177: =MATCH(A177,'Hoja 1'!G1:G892,0) -> #N/A
A180: =IFERROR(__xludf.DUMMYFUNCTION("QUERY('Hoja 1'!E1:E1000, ""SELECT * WHERE E=66162 OR E='66162' LIMIT 1"", 0)"),66162) -> 66162 | B180: =MATCH(A180,'Hoja 1'!G1:G892,0) -> #N/A
A183: =IFERROR(__xludf.DUMMYFUNCTION("QUERY('Hoja 1'!E1:E1000, ""SELECT * WHERE E=66162 OR E='66162' LIMIT 1"", 0)"),66162) -> 66162 | B183: =MATCH(A183,'Hoja 1'!G1:G892,0) -> #N/A
A186: =IFERROR(__xludf.DUMMYFUNCTION("QUERY('Hoja 1'!E1:E1000, ""SELECT * WHERE E=67634 OR E='67634' LIMIT 1"", 0)"),67634) -> 67634 | B186: =MATCH(A186,'Hoja 1'!G1:G892,0) -> #N/A
A189: =IFERROR(__xludf.DUMMYFUNCTION("QUERY('Hoja 1'!E1:E1000, ""SELECT * WHERE E=67634 OR E='67634' LIMIT 1"", 0)"),67634) -> 67634 | B189: =MATCH(A189,'Hoja 1'!G1:G892,0) -> #N/A
A192: =IFERROR(__xludf.DUMMYFUNCTION("QUERY('Hoja 1'!E1:E1000, ""SELECT * WHERE E=67634 OR E='67634' LIMIT 1"", 0)"),67634) -> 67634 | B192: =MATCH(A192,'Hoja 1'!G1:G892,0) -> #N/A
A195: =IFERROR(__xludf.DUMMYFUNCTION("QUERY('Hoja 1'!E1:E1000, ""SELECT * WHERE E=66162 OR E='66162' LIMIT 1"", 0)"),66162) -> 66162 | B195: =MATCH(A195,'Hoja 1'!G1:G892,0) -> #N/A
A198: =IFERROR(__xludf.DUMMYFUNCTION("QUERY('Hoja 1'!E1:E1000, ""SELECT * WHERE E=68143 OR E='68143' LIMIT 1"", 0)"),68143) -> 68143 | B198: =MATCH(A198,'Hoja 1'!G1:G892,0) -> #N/A
A201: =IFERROR(__xludf.DUMMYFUNCTION("QUERY('Hoja 1'!E1:E1000, ""SELECT * WHERE E=68143 OR E='68143' LIMIT 1"", 0)"),68143) -> 68143 | B201: =MATCH(A201,'Hoja 1'!G1:G892,0) -> #N/A
A204: =IFERROR(__xludf.DUMMYFUNCTION("QUERY('Hoja 1'!E1:E1000, ""SELECT * WHERE E=68143 OR E='68143' LIMIT 1"", 0)"),68143) -> 68143 | B204: =MATCH(A204,'Hoja 1'!G1:G892,0) -> #N/A
A207: =IFERROR(__xludf.DUMMYFUNCTION("QUERY('Hoja 1'!E1:E1000, ""SELECT * WHERE E=68143 OR E='68143' LIMIT 1"", 0)"),68143) -> 68143 | B207: =MATCH(A207,'Hoja 1'!G1:G892,0) -> #N/A
A210: =IFERROR(__xludf.DUMMYFUNCTION("QUERY('Hoja 1'!E1:E1000, ""SELECT * WHERE E=68096 OR E='68096' LIMIT 1"", 0)"),68096) -> 68096 | B210: =MATCH(A210,'Hoja 1'!G1:G892,0) -> #N/A
A213: =IFERROR(__xludf.DUMMYFUNCTION("QUERY('Hoja 1'!E1:E1000, ""SELECT * WHERE E=68096 OR E='68096' LIMIT 1"", 0)"),68096) -> 68096 | B213: =MATCH(A213,'Hoja 1'!G1:G892,0) -> #N/A
A216: =IFERROR(__xludf.DUMMYFUNCTION("QUERY('Hoja 1'!E1:E1000, ""SELECT * WHERE E=68096 OR E='68096' LIMIT 1"", 0)"),68096) -> 68096 | B216: =MATCH(A216,'Hoja 1'!G1:G892,0) -> #N/A
A219: =IFERROR(__xludf.DUMMYFUNCTION("QUERY('Hoja 1'!E1:E1000, ""SELECT * WHERE E=66454 OR E='66454' LIMIT 1"", 0)"),66454) -> 66454 | B219: =MATCH(A219,'Hoja 1'!G1:G892,0) -> #N/A
A222: =IFERROR(__xludf.DUMMYFUNCTION("QUERY('Hoja 1'!E1:E1000, ""SELECT * WHERE E=66454 OR E='66454' LIMIT 1"", 0)"),66454) -> 66454 | B222: =MATCH(A222,'Hoja 1'!G1:G892,0) -> #N/A
A225: =IFERROR(__xludf.DUMMYFUNCTION("QUERY('Hoja 1'!E1:E1000, ""SELECT * WHERE E=68137 OR E='68137' LIMIT 1"", 0)"),68137) -> 68137 | B225: =MATCH(A225,'Hoja 1'!G1:G892,0) -> #N/A
A228: =IFERROR(__xludf.DUMMYFUNCTION("QUERY('Hoja 1'!E1:E1000, ""SELECT * WHERE E=68137 OR E='68137' LIMIT 1"", 0)"),68137) -> 68137 | B228: =MATCH(A228,'Hoja 1'!G1:G892,0) -> #N/A
A231: =IFERROR(__xludf.DUMMYFUNCTION("QUERY('Hoja 1'!E1:E1000, ""SELECT * WHERE E=67008 OR E='67008' LIMIT 1"", 0)"),67008) -> 67008 | B231: =MATCH(A231,'Hoja 1'!G1:G892,0) -> #N/A
A234: =IFERROR(__xludf.DUMMYFUNCTION("QUERY('Hoja 1'!E1:E1000, ""SELECT * WHERE E=67008 OR E='67008' LIMIT 1"", 0)"),67008) -> 67008 | B234: =MATCH(A234,'Hoja 1'!G1:G892,0) -> #N/A
A237: =IFERROR(__xludf.DUMMYFUNCTION("QUERY('Hoja 1'!E1:E1000, ""SELECT * WHERE E=67008 OR E='67008' LIMIT 1"", 0)"),67008) -> 67008 | B237: =MATCH(A237,'Hoja 1'!G1:G892,0) -> #N/A
A240: =IFERROR(__xludf.DUMMYFUNCTION("QUERY('Hoja 1'!E1:E1000, ""SELECT * WHERE E=68263 OR E='68263' LIMIT 1"", 0)"),68263) -> 68263 | B240: =MATCH(A240,'Hoja 1'!G1:G892,0) -> #N/A
A243: =IFERROR(__xludf.DUMMYFUNCTION("QUERY('Hoja 1'!E1:E1000, ""SELECT * WHERE E=68263 OR E='68263' LIMIT 1"", 0)"),68263) -> 68263 | B243: =MATCH(A243,'Hoja 1'!G1:G892,0) -> #N/A
A246: =IFERROR(__xludf.DUMMYFUNCTION("QUERY('Hoja 1'!E1:E1000, ""SELECT * WHERE E=68263 OR E='68263' LIMIT 1"", 0)"),68263) -> 68263 | B246: =MATCH(A246,'Hoja 1'!G1:G892,0) -> #N/A
A249: =IFERROR(__xludf.DUMMYFUNCTION("QUERY('Hoja 1'!E1:E1000, ""SELECT * WHERE E=67217 OR E='67217' LIMIT 1"", 0)"),67217) -> 67217 | B249: =MATCH(A249,'Hoja 1'!G1:G892,0) -> #N/A
A252: =IFERROR(__xludf.DUMMYFUNCTION("QUERY('Hoja 1'!E1:E1000, ""SELECT * WHERE E=67217 OR E='67217' LIMIT 1"", 0)"),67217) -> 67217 | B252: =MATCH(A252,'Hoja 1'!G1:G892,0) -> #N/A
A255: =IFERROR(__xludf.DUMMYFUNCTION("QUERY('Hoja 1'!E1:E1000, ""SELECT * WHERE E=67217 OR E='67217' LIMIT 1"", 0)"),67217) -> 67217 | B255: =MATCH(A255,'Hoja 1'!G1:G892,0) -> #N/A
A258: =IFERROR(__xludf.DUMMYFUNCTION("QUERY('Hoja 1'!E1:E1000, ""SELECT * WHERE E=67217 OR E='67217' LIMIT 1"", 0)"),67217) -> 67217 | B258: =MATCH(A258,'Hoja 1'!G1:G892,0) -> #N/A
A261: =IFERROR(__xludf.DUMMYFUNCTION("QUERY('Hoja 1'!E1:E1000, ""SELECT * WHERE E=67217 OR E='67217' LIMIT 1"", 0)"),67217) -> 67217 | B261: =MATCH(A261,'Hoja 1'!G1:G892,0) -> #N/A
A264: =IFERROR(__xludf.DUMMYFUNCTION("QUERY('Hoja 1'!E1:E1000, ""SELECT * WHERE E=67217 OR E='67217' LIMIT 1"", 0)"),67217) -> 67217 | B264: =MATCH(A264,'Hoja 1'!G1:G892,0) -> #N/A
A267: =IFERROR(__xludf.DUMMYFUNCTION("QUERY('Hoja 1'!E1:E1000, ""SELECT * WHERE E=67217 OR E='67217' LIMIT 1"", 0)"),67217) -> 67217 | B267: =MATCH(A267,'Hoja 1'!G1:G892,0) -> #N/A
A270: =IFERROR(__xludf.DUMMYFUNCTION("QUERY('Hoja 1'!E1:E1000, ""SELECT * WHERE E=67840 OR E='67840' LIMIT 1"", 0)"),67840) -> 67840 | B270: =MATCH(A270,'Hoja 1'!G1:G892,0) -> #N/A
A273: =IFERROR(__xludf.DUMMYFUNCTION("QUERY('Hoja 1'!E1:E1000, ""SELECT * WHERE E=67840 OR E='67840' LIMIT 1"", 0)"),67840) -> 67840 | B273: =MATCH(A273,'Hoja 1'!G1:G892,0) -> #N/A
A276: =IFERROR(__xludf.DUMMYFUNCTION("QUERY('Hoja 1'!E1:E1000, ""SELECT * WHERE E=67840 OR E='67840' LIMIT 1"", 0)"),67840) -> 67840 | B276: =MATCH(A276,'Hoja 1'!G1:G892,0) -> #N/A
A279: =IFERROR(__xludf.DUMMYFUNCTION("QUERY('Hoja 1'!E1:E1000, ""SELECT * WHERE E=67978 OR E='67978' LIMIT 1"", 0)"),67978) -> 67978 | B279: =MATCH(A279,'Hoja 1'!G1:G892,0) -> #N/A
A282: =IFERROR(__xludf.DUMMYFUNCTION("QUERY('Hoja 1'!E1:E1000, ""SELECT * WHERE E=67978 OR E='67978' LIMIT 1"", 0)"),67978) -> 67978 | B282: =MATCH(A282,'Hoja 1'!G1:G892,0) -> #N/A
A285: =IFERROR(__xludf.DUMMYFUNCTION("QUERY('Hoja 1'!E1:E1000, ""SELECT * WHERE E=66564 OR E='66564' LIMIT 1"", 0)"),66564) -> 66564 | B285: =MATCH(A285,'Hoja 1'!G1:G892,0) -> #N/A
A288: =IFERROR(__xludf.DUMMYFUNCTION("QUERY('Hoja 1'!E1:E1000, ""SELECT * WHERE E=66564 OR E='66564' LIMIT 1"", 0)"),66564) -> 66564 | B288: =MATCH(A288,'Hoja 1'!G1:G892,0) -> #N/A
A291: =IFERROR(__xludf.DUMMYFUNCTION("QUERY('Hoja 1'!E1:E1000, ""SELECT * WHERE E=66564 OR E='66564' LIMIT 1"", 0)"),66564) -> 66564 | B291: =MATCH(A291,'Hoja 1'!G1:G892,0) -> #N/A
A294: =IFERROR(__xludf.DUMMYFUNCTION("QUERY('Hoja 1'!E1:E1000, ""SELECT * WHERE E=66564 OR E='66564' LIMIT 1"", 0)"),66564) -> 66564 | B294: =MATCH(A294,'Hoja 1'!G1:G892,0) -> #N/A
A297: =IFERROR(__xludf.DUMMYFUNCTION("QUERY('Hoja 1'!E1:E1000, ""SELECT * WHERE E=66564 OR E='66564' LIMIT 1"", 0)"),66564) -> 66564 | B297: =MATCH(A297,'Hoja 1'!G1:G892,0) -> #N/A
A300: =IFERROR(__xludf.DUMMYFUNCTION("QUERY('Hoja 1'!E1:E1000, ""SELECT * WHERE E=66564 OR E='66564' LIMIT 1"", 0)"),66564) -> 66564 | B300: =MATCH(A300,'Hoja 1'!G1:G892,0) -> #N/A
...
